src/dataMemory.v
`timescale 1ns / 1ps

// Data Memory : Stores data for load/store operations
//implements 4KB data emem for loading/storing operations in processor
//word-lined addressing
module dataMemory(
    input clk,           // Clock signal :synchronizes write op.
    input [31:0] addr,   // Byte address input
    input [31:0] wdata,  // Write data input
    input we,            // Write enable signal
    input re,            // Read enable
    output reg [31:0] rdata // Read data
);

//Memory declaration:
  //each memory location stores one 32 bit word.

    reg [31:0] memory [0:1023]; // 4KB data memory (1024 words) of 32 bits each

    // Initialize all memory locations to zero t startup for pred. behavior
    integer i;
    initial begin
        for (i = 0; i < 1024; i = i + 1) begin
            memory[i] = 32'd0; //set each memory to 32-bit zero
        end
    end

    // Read operation
    always @(*) begin
        if (re && addr[31:2] < 1024) begin
            rdata = memory[addr[31:2]]; // Word-aligned access
        end else begin
            rdata = 32'd0;
        end
    end

    // Write operation
    always @(posedge clk) begin
        if (we && addr[31:2] < 1024) begin
            memory[addr[31:2]] <= wdata;
        end
    end

endmodule

src/alu.v
`timescale 1ns / 1ps

// ALU Module  Performs arithmetic and logical operations
module alu(
    input [31:0] a,           // Input operand A
    input [31:0] b,           // Input operand B
    input [3:0] alu_control,  // Operation selector
    output reg [31:0] result, // ALU result
    output zero               // Zero flag
);

    // ALU operation codes : will come back to be implemented
    localparam ALU_ADD  = 4'b0000;
    localparam ALU_SUB  = 4'b0001;

    // need to: Implement ALU operations
    always @(*) begin
        result = 32'd0;  // Default output
    end

    // need to: Implement zero flag
    assign zero = (result == 32'd0);

endmodule

src/regfile.v
`timescale 1ns / 1ps

module regfile(
     input clk,              // Clock signal
    input rst,              // Reset signal
    input [4:0] rs1,        // Read address 1
    input [4:0] rs2,        // Read address 2
    input [4:0] rd,         // Write address
    input [31:0] wdata,     // Write data
    input we,               // Write enable
    output [31:0] rdata1,   // Read data 1
    output [31:0] rdata2    // Read data 2
);

    reg [31:0] registers [0:31]; //32 reg
    integer i;

    // Initialize all registers to zero
    integer i;
    initial begin
        for (i = 0; i < 32; i = i + 1) begin
            registers[i] = 32'd0;
        end
    end

    // Read ports :combinational
    assign rdata1 = (rs1 != 0) ? registers[rs1] : 32'd0;
    assign rdata2 = (rs2 != 0) ? registers[rs2] : 32'd0;

    // Write port : synchronous
    always @(posedge clk or posedge rst) begin
        if (rst) begin
          //reset all reg to zero
            for (i = 0; i < 32; i = i + 1) begin
                registers[i] <= 32'd0;
            end
        end else if (we && (rd != 0)) begin
          //write to register if not x0
            registers[rd] <= wdata;
        end
    end

endmodule

src/immediateGen.v
`timescale 1ns / 1ps
//immediate generator: extracts and sign exttends immediate val.

module immediateGen(
    input [31:0] instruction,
    input [1:0] imm_sel, //imm. format selector
    output reg [31:0] imm
);
//immediate value generation based on inst. format
    always @(*) begin
        case (imm_sel)
            2'b00: begin // I-type
                imm = {{20{instruction[31]}}, instruction[31:20]};
            end
            2'b01: begin // S-type
                imm = {{20{instruction[31]}}, instruction[31:25], instruction[11:7]};
            end
            2'b10: begin // B-type : [31], [30:25], [11:8]-shifted left by 1
                imm = {{20{instruction[31]}}, instruction[7], instruction[30:25], instruction[11:8], 1'b0};
            end
            2'b11: begin // U-type : shifted left by 12
                imm = {instruction[31:12], 12'b0};
            end
            default: imm = 32'd0;
        endcase
    end

endmodule

src/aluControl.v
`timescale 1ns / 1ps

module aluControl(
    input [1:0] alu_op, //ALu operation types
    input [2:0] funct3, //function3 field
    input [6:0] funct7, //fucntion7 field
    output reg [3:0] aluControl //ALU operation code
);
//ALU operatoin codes
    localparam ALU_ADD  = 4'b0000;
    localparam ALU_SUB  = 4'b0001;
    localparam ALU_AND  = 4'b0010;
    localparam ALU_OR   = 4'b0011;
    localparam ALU_XOR  = 4'b0100;
    localparam ALU_SLT  = 4'b1000;
    localparam ALU_SLL  = 4'b0101;
    localparam ALU_SRL  = 4'b0110;
    localparam ALU_SRA  = 4'b0111;
    localparam ALU_SLTU = 4'b1001;  // ADD THIS


//ALu control decoding
    always @(*) begin
        case (alu_op)
            2'b00: aluControl = ALU_ADD; //load/store : add for address calc
            2'b01: aluControl = ALU_SUB; //branch: substract for comparison
            2'b10: begin //r-type inst.
                case (funct3)
                    3'b000: aluControl = (funct7[5]) ? ALU_SUB : ALU_ADD;
                     3'b001: aluControl = ALU_SLL;   // Shift left logical
                     3'b010: aluControl = ALU_SLT;   // Set less than (signed)
                       3'b011: aluControl = ALU_SLTU;  // Set less than
                    3'b100: aluControl = ALU_XOR;

                     3'b101: aluControl = (funct7[5]) ? ALU_SRA : ALU_SRL;

                    3'b110: aluControl = ALU_OR;
                    3'b111: aluControl = ALU_AND;
                    default: aluControl = ALU_ADD;
                endcase
            end
            2'b11: begin //I-type inst.
                case (funct3)
                    3'b000: aluControl = ALU_ADD;
                    3'b001: aluControl = ALU_SLL;   // SLLI
                    3'b010: aluControl = ALU_SLT;   // SLTI
                    3'b011: aluControl = ALU_SLTU;  // SLTIU
                    3'b100: aluControl = ALU_XOR;   // XORI
                    3'b101: aluControl = (funct7[5]) ? ALU_SRA : ALU_SRL;

                    3'b111: aluControl = ALU_AND;
                    3'b110: aluControl = ALU_OR;
                    default: aluControl = ALU_ADD;
                endcase
            end
            default: aluControl = ALU_ADD;
        endcase
    end

endmodule

src/controlUnit.v
`timescale 1ns / 1ps
//control unit: generates signals from instruction opcode
module controlUnit(
    input [6:0] opcode, //inst opcode field
    input [2:0] funct3, //function3 field
    input [6:0] funct7, //function7 field
    output reg reg_write, //register write enable
    output reg alu_src, //ALU dource 0= register, 1 = immediate
    output reg mem_write, //memory write enable
    output reg mem_read, //mem read enable
    output reg mem_to_reg, //memory to register
    output reg branch, //branch inst
    output reg [1:0] alu_op, //ALU operation type
    output reg [1:0] imm_sel, //jump inst.
    output reg jump
);
//RISC-V RC32I opcodes

    localparam OP_RTYPE = 7'b0110011; // reg-reg operation
    localparam OP_ITYPE = 7'b0010011; //immediate operations
    localparam OP_LOAD  = 7'b0000011; //load instructions
    localparam OP_STORE = 7'b0100011; //store instructions
    localparam OP_BRANCH = 7'b1100011; //branchinstructions
    localparam OP_JAL   = 7'b1101111; //jump and link
    localparam OP_JALR  = 7'b1100111; //load upper immediate
    localparam OP_LUI   = 7'b0110111; //add upper imm.

//ALU operation types!
    localparam ALU_OP_RTYPE = 2'b10; //R-type instructions
    localparam ALU_OP_ITYPE = 2'b11; //I-type instructions
    localparam ALU_OP_BRANCH = 2'b01; //branch comparisons
    localparam ALU_OP_OTHER = 2'b00; //other op.

//imm format types
    localparam IMM_I = 2'b00; //i-type loads
    localparam IMM_S = 2'b01; //s-type stores
    localparam IMM_B = 2'b10; //b-type :branches
    localparam IMM_U = 2'b11; //U-type:LUI, AUIPC


//control signal generation based on opcode
    always @(*) begin
      //default control vals
        reg_write = 1'b0;
        alu_src = 1'b0;
        mem_write = 1'b0;
        mem_read = 1'b0;
        mem_to_reg = 1'b0;
        branch = 1'b0;
        alu_op = ALU_OP_OTHER;
        imm_sel = IMM_I;
        jump = 1'b0;

        case (opcode)
            OP_RTYPE: begin //add, sub, and, or ,axor,slt, sll,...
                reg_write = 1'b1; //write to register
                alu_src = 1'b0; //use register as ALU source
                alu_op = ALU_OP_RTYPE; //r-type ALU operation
            end
            OP_ITYPE: begin //addi, andi, ori, xori,slti,slli,srli,...
                reg_write = 1'b1;
                alu_src = 1'b1; //use imm. as ALU source
                alu_op = ALU_OP_ITYPE; //I-type ALU operation
                imm_sel = IMM_I; //I-type imm. format
            end

            OP_LOAD: begin //lw
                reg_write = 1'b1;
                alu_src = 1'b1; //use imm for address offset
                mem_read = 1'b1; //read from memory
                mem_to_reg = 1'b1; //write memory data to register
                imm_sel = IMM_I; //I-type imm format
            end

            OP_STORE: begin //sw
                alu_src = 1'b1; //for imm address offset
                mem_write = 1'b1; //write to memory
                imm_sel = IMM_S; //s-type imm format
            end

            OP_BRANCH: begin //beq, bne, blt, bge
                branch = 1'b1; //branch instruc.
                alu_op = ALU_OP_BRANCH; //branch comparison
                imm_sel = IMM_B; //b-type immed. format
            end

            OP_JAL: begin
                reg_write = 1'b1;  // Write return address to register
                jump = 1'b1;  // Jump instruction
                imm_sel = IMM_U;  // U-type immediate format
            end
            default: begin
                // Safe defaults
            end
        endcase
    end

endmodule

src/instructionMemory.v
`timescale 1ns / 1ps

module instructionMemory(
    input [31:0] addr,
    output reg [31:0] data,
    output reg imem_error
);

    reg [31:0] memory [0:1023];
    integer i; //for loop var

    initial begin
        // Initialize all memory to zero first
        for (i = 0; i < 1024; i = i + 1) begin
            memory[i] = 32'd0;
        end

        // Load program from hex file
        $readmemh("tests/test_base.hex", memory);
        imem_error = 1'b0;
    end

    always @(*) begin
        if (addr[1:0] != 2'b00) begin
            $display("Unaligned instruction fetch: addr=0x%h", addr);
            data = 32'h00000013; // nop instruction
            imem_error = 1'b1;
        end else if (addr[31:2] >= 1024) begin
            $display("Instruction fetch out of bounds: addr=0x%h", addr);
            data = 32'h00000013;
            imem_error = 1'b1;
        end else begin
            data = memory[addr[31:2]];
            imem_error = 1'b0;
        end
    end

endmodule

src/pcRegister.v
`timescale 1ns / 1ps

//Program Counter Register: holds current instruction address

module pcRegister(
    input clk,
    input rst,
    input [31:0] next_pc,
    output reg [31:0] pc
);

//Prog counter update

    always @(posedge clk or posedge rst) begin
        if (rst) begin
            pc <= 32'd0; //reset to start at address 0
        end else begin
            pc <= next_pc; //update to next inst. address
        end
    end

endmodule

src/cpu.v
//main cpu module!
//todo: add more comments later!
`timescale 1ns / 1ps

module cpu(
    input clk, //clock input
    input rst //reset input
);

    // Instruction Fetch
    wire [31:0] pc; //program counter
    wire [31:0] instruction; //current instruction

    // Instruction Decode
    wire [6:0] opcode;
    wire [4:0] rs1, rs2, rd; //register addresses
    wire [2:0] funct3;
    wire [6:0] funct7;
    wire [31:0] imm; //immediate value

    // Control Signals
    wire reg_write, alu_src, mem_write, mem_read, mem_to_reg, branch;
    wire [1:0] alu_op, imm_sel;
    wire jump;
    wire [3:0] alu_control_sig;

    // Datapath
    wire [31:0] rdata1, rdata2, wdata;
    wire [31:0] alu_result, alu_b, mem_rdata;
    wire alu_zero;

    // Program Counter Control
    wire pc_src;
    wire [31:0] pc_plus_4;
    wire [31:0] branch_target;
    wire [31:0] next_pc;

    // Module Instantiations
    pcRegister pc_reg_inst(.clk(clk), .rst(rst), .next_pc(next_pc), .pc(pc));

    instructionMemory imem(.addr(pc), .data(instruction));

//instruction field opcode
    assign opcode = instruction[6:0];
    assign rd = instruction[11:7];
    assign funct3 = instruction[14:12];
    assign rs1 = instruction[19:15];
    assign rs2 = instruction[24:20];
    assign funct7 = instruction[31:25];

//main control unit
    controlUnit control(
        .opcode(opcode),
        .funct3(funct3),
        .funct7(funct7),
        .reg_write(reg_write),
        .alu_src(alu_src),
        .mem_write(mem_write),
        .mem_read(mem_read),
        .mem_to_reg(mem_to_reg),
        .branch(branch),
        .alu_op(alu_op),
        .imm_sel(imm_sel),
        .jump(jump)
    );
//ALU control
    aluControl alu_ctrl(
        .alu_op(alu_op),
        .funct3(funct3),
        .funct7(funct7),
        .aluControl(alu_control_sig)
    );
//immediate generator
    immediateGen imm_gen(
        .instruction(instruction),
        .imm_sel(imm_sel),
        .imm(imm)
    );

    regfile regfile_inst(
        .clk(clk),
        .rst(rst),
        .rs1(rs1),
        .rs2(rs2),
        .rd(rd),
        .wdata(wdata),
        .we(reg_write),
        .rdata1(rdata1),
        .rdata2(rdata2)
    );
//ALU input B multiplexer
    assign alu_b = alu_src ? imm : rdata2;
//arithmetic logic unit
    alu alu_inst(
        .a(rdata1),
        .b(alu_b),
        .alu_control(alu_control_sig),
        .result(alu_result),
        .zero(alu_zero)
    );
//data memory
    dataMemory dmem(
        .clk(clk),
        .addr(alu_result),
        .wdata(rdata2),
        .we(mem_write),
        .re(mem_read),
        .rdata(mem_rdata)
    );

    assign wdata = mem_to_reg ? mem_rdata : alu_result;

    // Next PC Calculation
    assign pc_src = branch & alu_zero;
    assign pc_plus_4 = pc + 4;
    assign branch_target = pc + imm;
    assign next_pc = jump ? branch_target : (pc_src ? branch_target : pc_plus_4);

endmodule

tests/testbench.v
`timescale 1ns / 1ps


//testbench:

module testbench;
    reg clk; //test clock
    reg rst; //test reset


//instantiate cpu
    cpu dut(.clk(clk), .rst(rst));

//clock genreation: 100MHz clock
    always #5 clk = ~clk;

//test sequence
    initial begin
      //init signals
        clk = 0;
        rst = 1;

//create waveform file for debugging
        $dumpfile("sim/tb.vcd");
        $dumpvars(0, testbench);

        $display("*** RISC-V CPU Testbench Starting ***");


//apply reset
        #20;
        rst = 0;
        $display("Reset released");


//run simulation for enough cycles to complete test prog.
       #1000; //run for 1000 times units


//display final results
        $display("\n** Simulation Results **");
        $display("Final PC: 0x%h", dut.pc);

        $display("\nSimulation completed");
        $finish;
    end


//monitor important signals for each clock cycle
    always @(posedge clk) begin
        if (!rst) begin
            $display("Cycle %0d: PC=0x%h", $time/10, dut.pc);
        end
    end

endmodule

sim/tb.vcd
$date
	Sun Nov 16 17:03:04 2025
$end
$version
	Icarus Verilog
$end
$timescale
	1ps
$end
$scope module testbench $end
$var reg 1 ! clk $end
$var reg 1 " rst $end
$scope module dut $end
$var wire 1 ! clk $end
$var wire 1 # pc_src $end
$var wire 1 " rst $end
$var wire 32 $ wdata [31:0] $end
$var wire 5 % rs2 [4:0] $end
$var wire 5 & rs1 [4:0] $end
$var wire 1 ' reg_write $end
$var wire 32 ( rdata2 [31:0] $end
$var wire 32 ) rdata1 [31:0] $end
$var wire 5 * rd [4:0] $end
$var wire 32 + pc_plus_4 [31:0] $end
$var wire 32 , pc [31:0] $end
$var wire 7 - opcode [6:0] $end
$var wire 32 . next_pc [31:0] $end
$var wire 1 / mem_write $end
$var wire 1 0 mem_to_reg $end
$var wire 1 1 mem_read $end
$var wire 32 2 mem_rdata [31:0] $end
$var wire 1 3 jump $end
$var wire 32 4 instruction [31:0] $end
$var wire 2 5 imm_sel [1:0] $end
$var wire 32 6 imm [31:0] $end
$var wire 7 7 funct7 [6:0] $end
$var wire 3 8 funct3 [2:0] $end
$var wire 32 9 branch_target [31:0] $end
$var wire 1 : branch $end
$var wire 1 ; alu_zero $end
$var wire 1 < alu_src $end
$var wire 32 = alu_result [31:0] $end
$var wire 2 > alu_op [1:0] $end
$var wire 4 ? alu_control_sig [3:0] $end
$var wire 32 @ alu_b [31:0] $end
$scope module alu_ctrl $end
$var wire 3 A funct3 [2:0] $end
$var wire 7 B funct7 [6:0] $end
$var wire 2 C alu_op [1:0] $end
$var reg 4 D aluControl [3:0] $end
$upscope $end
$scope module alu_inst $end
$var wire 4 E alu_control [3:0] $end
$var wire 32 F b [31:0] $end
$var wire 1 ; zero $end
$var wire 32 G a [31:0] $end
$var reg 32 H result [31:0] $end
$upscope $end
$scope module control $end
$var wire 3 I funct3 [2:0] $end
$var wire 7 J funct7 [6:0] $end
$var wire 7 K opcode [6:0] $end
$var reg 2 L alu_op [1:0] $end
$var reg 1 < alu_src $end
$var reg 1 : branch $end
$var reg 2 M imm_sel [1:0] $end
$var reg 1 3 jump $end
$var reg 1 1 mem_read $end
$var reg 1 0 mem_to_reg $end
$var reg 1 / mem_write $end
$var reg 1 ' reg_write $end
$upscope $end
$scope module dmem $end
$var wire 32 N addr [31:0] $end
$var wire 1 ! clk $end
$var wire 1 1 re $end
$var wire 1 / we $end
$var wire 32 O wdata [31:0] $end
$var reg 32 P rdata [31:0] $end
$var integer 32 Q i [31:0] $end
$upscope $end
$scope module imem $end
$var wire 32 R addr [31:0] $end
$var reg 32 S data [31:0] $end
$var reg 1 T imem_error $end
$var integer 32 U i [31:0] $end
$upscope $end
$scope module imm_gen $end
$var wire 2 V imm_sel [1:0] $end
$var wire 32 W instruction [31:0] $end
$var reg 32 X imm [31:0] $end
$upscope $end
$scope module pc_reg_inst $end
$var wire 1 ! clk $end
$var wire 32 Y next_pc [31:0] $end
$var wire 1 " rst $end
$var reg 32 Z pc [31:0] $end
$upscope $end
$scope module regfile_inst $end
$var wire 1 ! clk $end
$var wire 5 [ rd [4:0] $end
$var wire 5 \ rs1 [4:0] $end
$var wire 5 ] rs2 [4:0] $end
$var wire 1 " rst $end
$var wire 32 ^ wdata [31:0] $end
$var wire 1 ' we $end
$var wire 32 _ rdata2 [31:0] $end
$var wire 32 ` rdata1 [31:0] $end
$var integer 32 a i [31:0] $end
$upscope $end
$upscope $end
$upscope $end
$enddefinitions $end
#0
$dumpvars
b100000 a
b0 `
b0 _
b101 ^
b101 ]
b0 \
b1 [
b0 Z
b100 Y
b101 X
b10100000000000010010011 W
b0 V
b10000000000 U
0T
b10100000000000010010011 S
b0 R
b10000000000 Q
b0 P
b0 O
b101 N
b0 M
b11 L
b10011 K
b0 J
b0 I
b101 H
b0 G
b101 F
b0 E
b0 D
b11 C
b0 B
b0 A
b101 @
b0 ?
b11 >
b101 =
1<
0;
0:
b101 9
b0 8
b0 7
b101 6
b0 5
b10100000000000010010011 4
03
b0 2
01
00
0/
b100 .
b10011 -
b0 ,
b100 +
b1 *
b0 )
b0 (
1'
b0 &
b101 %
b101 $
0#
1"
0!
$end
#5000
b100000 a
1!
#10000
0!
#15000
b100000 a
1!
#20000
0!
0"
#25000
b1010 $
b1010 ^
b1010 =
b1010 H
b1010 N
b1010 @
b1010 F
b1000 .
b1000 Y
b1010 6
b1010 X
b1010 %
b1010 ]
b10 *
b10 [
b101000000000000100010011 4
b101000000000000100010011 S
b101000000000000100010011 W
b1110 9
b1000 +
b100 ,
b100 R
b100 Z
1!
#30000
0!
#35000
b1111 $
b1111 ^
b1111 =
b1111 H
b1111 N
b1010 (
b1010 O
b1010 _
b101 )
b101 G
b101 `
b10 >
b10 C
b10 L
0<
1'
b1100 .
b1100 Y
b10 6
b10 X
b10 %
b10 ]
b1 &
b1 \
b11 *
b11 [
b110011 -
b110011 K
b1000001000000110110011 4
b1000001000000110110011 S
b1000001000000110110011 W
b1010 9
b1100 +
b1000 ,
b1000 R
b1000 Z
1!
#40000
0!
#45000
b101 $
b101 ^
b101 @
b101 F
0;
b101 =
b101 H
b101 N
b1 ?
b1 D
b1 E
b101 (
b101 O
b101 _
b1010 )
b1010 G
b1010 `
b10000 .
b10000 Y
b10000000001 6
b10000000001 X
b100000 7
b100000 B
b100000 J
b1 %
b1 ]
b10 &
b10 \
b100 *
b100 [
b1000000000100010000001000110011 4
b1000000000100010000001000110011 S
b1000000000100010000001000110011 W
b10000001101 9
b10000 +
b1100 ,
b1100 R
b1100 Z
1!
#50000
0!
#55000
b10000000000001010 $
b10000000000001010 ^
b10000000000001010 =
b10000000000001010 H
b10000000000001010 N
b10000000000000000 @
b10000000000000000 F
b0 ?
b0 D
b0 E
b0 (
b0 O
b0 _
b11 5
b11 M
b11 V
1<
b0 >
b0 C
b0 L
1'
b10100 .
b10100 Y
b10000000000000000 6
b10000000000000000 X
b0 7
b0 B
b0 J
b0 %
b0 ]
b101 *
b101 [
b110111 -
b110111 K
b10000001010110111 4
b10000001010110111 S
b10000001010110111 W
b10000000000010000 9
b10100 +
b10000 ,
b10000 R
b10000 Z
1!
#60000
0!
#65000
b10000000000001010 $
b10000000000001010 ^
b10000000000001010 =
b10000000000001010 H
b10000000000001010 N
b0 @
b0 F
b1111 (
b1111 O
b1111 _
b10000000000001010 )
b10000000000001010 G
b10000000000001010 `
1/
b1 5
b1 M
b1 V
1<
0'
b11000 .
b11000 Y
b0 6
b0 X
b11 %
b11 ]
b101 &
b101 \
b10 8
b10 A
b10 I
b0 *
b0 [
b100011 -
b100011 K
b1100101010000000100011 4
b1100101010000000100011 S
b1100101010000000100011 W
b10100 9
b11000 +
b10100 ,
b10100 R
b10100 Z
1!
#70000
0!
#75000
b10000000000001010 =
b10000000000001010 H
b10000000000001010 N
b0 $
b0 ^
b0 @
b0 F
b0 (
b0 O
b0 _
10
11
1'
b0 5
b0 M
b0 V
0/
1<
b11100 .
b11100 Y
b0 6
b0 X
b0 %
b0 ]
b100 *
b100 [
b11 -
b11 K
b101010001000000011 4
b101010001000000011 S
b101010001000000011 W
b11000 9
b11100 +
b11000 ,
b11000 R
b11000 Z
1!
#80000
0!
#85000
b1111 =
b1111 H
b1111 N
b1111 $
b1111 ^
b1111 )
b1111 G
b1111 `
b1 ?
b1 D
b1 E
b10 5
b10 M
b10 V
b1 >
b1 C
b1 L
1:
00
01
0<
0'
b100000 .
b100000 Y
b1000 6
b1000 X
b100 %
b100 ]
b11 &
b11 \
b0 8
b0 A
b0 I
b1000 *
b1000 [
b1100011 -
b1100011 K
b10000011000010001100011 4
b10000011000010001100011 S
b10000011000010001100011 W
b100100 9
b100000 +
b11100 ,
b11100 R
b11100 Z
1!
#90000
0!
#95000
b1 $
b1 ^
b1 =
b1 H
b1 N
b1 @
b1 F
b0 ?
b0 D
b0 E
b101 (
b101 O
b101 _
b0 )
b0 G
b0 `
1<
1'
b0 5
b0 M
b0 V
b11 >
b11 C
b11 L
0:
b100100 .
b100100 Y
b1 6
b1 X
b1 %
b1 ]
b0 &
b0 \
b110 *
b110 [
b10011 -
b10011 K
b100000000001100010011 4
b100000000001100010011 S
b100000000001100010011 W
b100001 9
b100100 +
b100000 ,
b100000 R
b100000 Z
1!
#100000
0!
#105000
b10 $
b10 ^
b10 =
b10 H
b10 N
b10 @
b10 F
b1010 (
b1010 O
b1010 _
b101000 .
b101000 Y
b10 6
b10 X
b10 %
b10 ]
b1000000000001100010011 4
b1000000000001100010011 S
b1000000000001100010011 W
b100110 9
b101000 +
b100100 ,
b100100 R
b100100 Z
1!
#110000
0!
#115000
b0 $
b0 ^
1;
b0 =
b0 H
b0 N
b0 @
b0 F
b0 (
b0 O
b0 _
b11 5
b11 M
b11 V
13
b0 >
b0 C
b0 L
0<
1'
b101000 .
b101000 Y
b0 6
b0 X
b0 %
b0 ]
b0 *
b0 [
b1101111 -
b1101111 K
b1101111 4
b1101111 S
b1101111 W
b101000 9
b101100 +
b101000 ,
b101000 R
b101000 Z
1!
